MANIFEST.in
README.rst
setup.py
django_stripe_payments.egg-info/PKG-INFO
django_stripe_payments.egg-info/SOURCES.txt
django_stripe_payments.egg-info/dependency_links.txt
django_stripe_payments.egg-info/not-zip-safe
django_stripe_payments.egg-info/requires.txt
django_stripe_payments.egg-info/top_level.txt
payments/__init__.py
payments/admin.py
payments/context_processors.py
payments/forms.py
payments/models.py
payments/settings.py
payments/signals.py
payments/urls.py
payments/views.py
payments/management/__init__.py
payments/management/commands/__init__.py
payments/management/commands/init_customers.py
payments/management/commands/init_plans.py
payments/templates/payments/_cancel_form.html
payments/templates/payments/_change_card_form.html
payments/templates/payments/_change_plan_form.html
payments/templates/payments/_subscribe_form.html
payments/templates/payments/_subscription_status.html
payments/templates/payments/base.html
payments/templates/payments/cancel.html
payments/templates/payments/change_card.html
payments/templates/payments/change_plan.html
payments/templates/payments/history.html
payments/templates/payments/subscribe.html
payments/templates/payments/email/body.txt
payments/templates/payments/email/body_base.txt
payments/templates/payments/email/subject.txt
payments/templatetags/__init__.py
payments/templatetags/payments_tags.py