Metadata-Version: 1.1
Name: django-stripe-payments
Version: 1.3
Summary: a payments Django app for Stripe
Home-page: https://github.com/eldarion/django-stripe-payments
Author: Patrick Altman
Author-email: paltman@eldarion.com
License: BSD
Platform: UNKNOWN
Classifier: Development Status :: 3 - Alpha
Classifier: Environment :: Web Environment
Classifier: Intended Audience :: Developers
Classifier: License :: OSI Approved :: BSD License
Classifier: Operating System :: OS Independent
Classifier: Programming Language :: Python
Classifier: Framework :: Django
